gradle.properties
hexdoc_hexahere/__gradle_version__.py
hexdoc_hexahere/__init__.py
hexdoc_hexahere/__version__.py
hexdoc_hexahere/_hooks.py
hexdoc_hexahere/py.typed
hexdoc_hexahere/_export/.gitignore
hexdoc_hexahere/_export/__init__.py
hexdoc_hexahere/_export/generated/__init__.py
hexdoc_hexahere/_export/generated/hexahere.hexdoc.json
hexdoc_hexahere/_export/generated/hexahere.patterns.hexdoc.json
hexdoc_hexahere/_export/generated/assets/hexahere/lang/en_us.flatten.json5
hexdoc_hexahere/_export/generated/assets/hexcasting/patchouli_books/thehexbook/en_us/entries/patterns/consts.json5
hexdoc_hexahere/_export/generated/assets/hexcasting/patchouli_books/thehexbook/en_us/entries/patterns/patterns.json5
hexdoc_hexahere/_export/generated/data/hexcasting/tags/action/per_world_pattern.json
hexdoc_hexahere/_templates/__init__.py
hexdoc_hexahere-0.1.1.1.20.1.1.0.dist-info/METADATA
hexdoc_hexahere-0.1.1.1.20.1.1.0.dist-info/WHEEL
hexdoc_hexahere-0.1.1.1.20.1.1.0.dist-info/entry_points.txt
hexdoc_hexahere-0.1.1.1.20.1.1.0.dist-info/licenses/LICENSE
hexdoc_hexahere-0.1.1.1.20.1.1.0.dist-info/RECORD
