Metadata-Version: 2.4
Name: hexdoc-hexahere
Version: 0.1.1.1.20.1.1.0
Summary: small utils for hexcasting
Project-URL: Homepage, https://astroorbis.github.io/Hexahere
Project-URL: Source, https://github.com/AstroOrbis/Hexahere
Author: AstroOrbis
License-File: LICENSE
Keywords: hexdoc
Requires-Python: >=3.12
Requires-Dist: hexdoc-hexcasting~=0.11.2.1.0
